[
  {
    "id": "5be1cbea-6e56-4b68-802d-1a1a0e94dc11",
    "source": "Софийска вода",
    "service_type": "water",
    "city": "София",
    "district": "Младост",
    "area": "ул. Александър Малинов 50",
    "type": "Аварийно спиране",
    "category": "emergency",
    "severity": "high",
    "start": "2025-06-09T09:00:00+03:00",
    "end": "2025-06-09T15:00:00+03:00",
    "timestamp": "2025-06-09T08:45:00+03:00",
    "description": "Спукана тръба – прекъсване на водоподаването."
  },
  {
    "id": "84f38c99-3ac6-4b0e-9b57-509303c68cbf",
    "source": "ЧЕЗ България",
    "service_type": "electricity",
    "city": "Пловдив",
    "district": "Централен",
    "area": "ул. Отец Паисий 14",
    "type": "Планирано спиране",
    "category": "scheduled",
    "severity": "low",
    "start": "2025-06-10T08:00:00+03:00",
    "end": "2025-06-10T11:00:00+03:00",
    "timestamp": "2025-06-09T16:00:00+03:00",
    "description": "Профилактика на електрическа подстанция."
  },
  {
    "id": "bd2c8d0e-9fc2-45c1-b2ea-fb8f4a40b1c9",
    "source": "Топлофикация София",
    "service_type": "heating",
    "city": "София",
    "district": "Лозенец",
    "area": "ул. Свети Наум 32",
    "type": "Планирано спиране",
    "category": "scheduled",
    "severity": "medium",
    "start": "2025-06-11T06:00:00+03:00",
    "end": "2025-06-11T18:00:00+03:00",
    "timestamp": "2025-06-09T10:00:00+03:00",
    "description": "Профилактика на топлопреносната мрежа – спиране на топлата вода."
  },
  {
    "id": "7ef7123e-2632-4df3-83b7-79819e31e1ee",
    "source": "ЧЕЗ България",
    "service_type": "electricity",
    "city": "Варна",
    "district": "Одесос",
    "area": "бул. Владислав Варненчик 90",
    "type": "Аварийно спиране",
    "category": "emergency",
    "severity": "high",
    "start": "2025-06-09T14:30:00+03:00",
    "end": "2025-06-09T18:00:00+03:00",
    "timestamp": "2025-06-09T14:00:00+03:00",
    "description": "Авария по мрежата – временно прекъсване на електрозахранването."
  },
  {
    "id": "b8f3a763-c9c3-4b47-a9a3-2b148c5eafc1",
    "source": "Топлофикация София",
    "service_type": "heating",
    "city": "София",
    "district": "Красно село",
    "area": "ул. Дойран 20",
    "type": "Аварийно спиране",
    "category": "emergency",
    "severity": "medium",
    "start": "2025-06-08T22:00:00+03:00",
    "end": "2025-06-09T08:00:00+03:00",
    "timestamp": "2025-06-08T21:50:00+03:00",
    "description": "Авария в абонатна станция – спиране на топлата вода през нощта."
  }
]
